django_hstore_field/__init__.py
django_hstore_field/fields.py
django_hstore_field-0.0.4.dist-info/METADATA
django_hstore_field-0.0.4.dist-info/WHEEL
django_hstore_field-0.0.4.dist-info/RECORD
